viperline/__init__.py
viperline/core.py
viperline-0.0.4.dist-info/LICENSE
viperline-0.0.4.dist-info/METADATA
viperline-0.0.4.dist-info/WHEEL
viperline-0.0.4.dist-info/top_level.txt
viperline-0.0.4.dist-info/RECORD
