Metadata-Version: 2.1
Name: viperline
Version: 0.0.4
Summary: Build performant and resilient data pipelines
Home-page: https://github.com/ejvelasco/viperline
Author: Eduardo J. Velasco
Author-email: velasco810@gmail.com
License: UNKNOWN
Platform: UNKNOWN
Classifier: Programming Language :: Python :: 3
Classifier: License :: OSI Approved :: MIT License
Classifier: Operating System :: OS Independent
Requires-Python: >=3.6
